nexus_cli/__init__.py
nexus_cli/__main__.py
nexus_cli/commands/__init__.py
nexus_cli/commands/compile.py
nexus_cli/commands/gateway.py
nexus_cli/commands/init.py
nexus_cli/commands/plugin.py
nexus_cli/commands/run.py
nexus_cli/commands/schema.py
nexus_cli/commands/status.py
nexus_core/__init__.py
nexus_core/compiler.py
nexus_core/errors.py
nexus_core/logging.py
nexus_core/memory.py
nexus_core/orchestrator.py
nexus_core/parser.py
nexus_core/schema_loader.py
nexus_core/sync.py
nexus_core/type_generator.py
nexus_core/validator.py
nexus_core/adapters/web/server.py
nexus_core/enterprise/__init__.py
nexus_core/enterprise/auth.py
nexus_core/enterprise/crypto.py
nexus_core/enterprise/persistence.py
nexus_core/frontend/__init__.py
nexus_core/plugins/__init__.py
nexus_core/realtime/__init__.py
nexus_core/realtime/events.py
nexus_core/realtime/gateway.py
nexus_core/realtime/pubsub.py
nexus_core/tests/__init__.py
nexus_core/tests/test_errors.py
nexus_core/tests/test_sync.py
nexus_core/tests/test_validator.py
nexus_lang-1.1.0.dist-info/licenses/LICENSE
nexus_lang-1.1.0.dist-info/METADATA
nexus_lang-1.1.0.dist-info/WHEEL
nexus_lang-1.1.0.dist-info/entry_points.txt
nexus_lang-1.1.0.dist-info/top_level.txt
nexus_lang-1.1.0.dist-info/RECORD
