Metadata-Version: 2.4
Name: nexus-lang
Version: 1.1.0
Summary: The Universal Polyglot Runtime - Write Python, C, Rust, Java in one file with zero-copy shared memory
Author: Nexus Team
License: MIT
Project-URL: Homepage, https://github.com/nexus-lang/nexus
Project-URL: Documentation, https://nexus-lang.dev/docs
Project-URL: Repository, https://github.com/nexus-lang/nexus
Project-URL: Issues, https://github.com/nexus-lang/nexus/issues
Keywords: polyglot,shared-memory,ipc,ffi,multi-language,runtime,websocket,realtime
Classifier: Development Status :: 3 - Alpha
Classifier: Intended Audience :: Developers
Classifier: License :: OSI Approved :: MIT License
Classifier: Operating System :: OS Independent
Classifier: Programming Language :: Python :: 3
Classifier: Programming Language :: Python :: 3.8
Classifier: Programming Language :: Python :: 3.9
Classifier: Programming Language :: Python :: 3.10
Classifier: Programming Language :: Python :: 3.11
Classifier: Programming Language :: Python :: 3.12
Classifier: Topic :: Software Development :: Compilers
Classifier: Topic :: Software Development :: Interpreters
Requires-Python: >=3.8
License-File: LICENSE
Requires-Dist: click>=8.0
Requires-Dist: colorama>=0.4
Requires-Dist: uvicorn>=0.20
Requires-Dist: fastapi>=0.100
Requires-Dist: websockets>=11.0
Provides-Extra: dev
Requires-Dist: pytest>=7.0; extra == "dev"
Requires-Dist: pytest-cov>=4.0; extra == "dev"
Requires-Dist: black>=23.0; extra == "dev"
Requires-Dist: mypy>=1.0; extra == "dev"
Requires-Dist: ruff>=0.1; extra == "dev"
Dynamic: license-file
